malware_local.py
malware_local_python.py
malware_transform.py
malware_transform_python.py
dpk_malware_transform_python-0.2.0.dist-info/METADATA
dpk_malware_transform_python-0.2.0.dist-info/WHEEL
dpk_malware_transform_python-0.2.0.dist-info/top_level.txt
dpk_malware_transform_python-0.2.0.dist-info/RECORD
